semantics2021_toy_languages/L1.py
semantics2021_toy_languages/__init__.py
semantics2021_toy_languages/__main__.py
semantics2021_toy_languages/_metadata.py
semantics2021_toy_languages-1.1.0.dist-info/METADATA
semantics2021_toy_languages-1.1.0.dist-info/WHEEL
semantics2021_toy_languages-1.1.0.dist-info/top_level.txt
semantics2021_toy_languages-1.1.0.dist-info/RECORD
