Metadata-Version: 2.1
Name: semantics2021-toy-languages
Version: 1.1.0
Summary: A Python implementation of the toy languages used in Part IB "Semantics of Programming Languages" (2020 - 2021)
Home-page: https://github.com/MitalAshok/semantics2021_toy_languages
Author: Mital Ashok
Author-email: ma880@cam.ac.uk
License: UNKNOWN
Platform: any
